[
  {
    "file": "img_0239.jpeg",
    "title": "🫠 nostrils in hd",
    "roll": "roll-001"
  },
  {
    "file": "img_0238.jpeg",
    "title": "🧊 cool guy verification",
    "roll": "roll-001"
  },
  {
    "file": "img_0235.jpeg",
    "title": "🐺 main character energy",
    "roll": "roll-001"
  },
  {
    "file": "img_0234.jpeg",
    "title": "🦞 claw and awe",
    "roll": "roll-001"
  },
  {
    "file": "img_0244.jpeg",
    "title": "🌪️ wind up merchant",
    "roll": "roll-001"
  },
  {
    "file": "img_0256.jpeg",
    "title": "🦅 briefly airborne",
    "roll": "roll-001"
  },
  {
    "file": "img_0253.jpeg",
    "title": "🚀 defying several laws",
    "roll": "roll-001"
  },
  {
    "file": "img_0245.jpeg",
    "title": "🫂 tactical debrief huddle",
    "roll": "roll-001"
  },
  {
    "file": "img_0267.jpeg",
    "title": "🧿 radiant bleacher angel",
    "roll": "roll-001"
  },
  {
    "file": "img_0272.jpeg",
    "title": "🫥 thousand yard stare",
    "roll": "roll-001"
  },
  {
    "file": "img_0271.jpeg",
    "title": "🫵 you're next buddy",
    "roll": "roll-001"
  },
  {
    "file": "img_0306.jpeg",
    "roll": "roll-001"
  },
  {
    "file": "img_0305.jpeg",
    "roll": "roll-001"
  },
  {
    "file": "img_0304.jpeg",
    "roll": "roll-001"
  },
  {
    "file": "img_0303.jpeg",
    "roll": "roll-001"
  },
  {
    "file": "img_0300.jpeg",
    "roll": "roll-001"
  },
  {
    "file": "img_0299.jpeg",
    "roll": "roll-001"
  },
  {
    "file": "img_0298.jpeg",
    "roll": "roll-001"
  },
  {
    "file": "img_0296.jpeg",
    "roll": "roll-001"
  }
]
